MANIFEST.in
README.rst
setup.cfg
setup.py
django_admin_history.egg-info/PKG-INFO
django_admin_history.egg-info/SOURCES.txt
django_admin_history.egg-info/dependency_links.txt
django_admin_history.egg-info/top_level.txt
django_history/__init__.py
django_history/admin.py
django_history/apps.py
django_history/defaults.py
django_history/middleware.py
django_history/models.py
django_history/signals.py
django_history/utils.py
django_history/__pycache__/__init__.cpython-37.pyc
django_history/__pycache__/admin.cpython-37.pyc
django_history/__pycache__/apps.cpython-37.pyc
django_history/__pycache__/defaults.cpython-37.pyc
django_history/__pycache__/middleware.cpython-37.pyc
django_history/__pycache__/models.cpython-37.pyc
django_history/__pycache__/signals.cpython-37.pyc
django_history/__pycache__/utils.cpython-37.pyc
django_history/locale/en/LC_MESSAGES/django.mo
django_history/locale/en/LC_MESSAGES/django.po
django_history/migrations/0001_initial.py
django_history/migrations/0002_auto_20210624_1414.py
django_history/migrations/0003_auto_20210815_1815.py
django_history/migrations/__init__.py
django_history/migrations/__pycache__/0001_initial.cpython-37.pyc
django_history/migrations/__pycache__/0002_auto_20210624_1414.cpython-37.pyc
django_history/migrations/__pycache__/0003_auto_20210815_1815.cpython-37.pyc
django_history/migrations/__pycache__/__init__.cpython-37.pyc
django_history/templates/history/admin/list.html